__init__.py
gdrive.py
main.py
pull.py
push.py
Auto_ReAuth_GSync-0.1.2.dist-info/LICENSE
Auto_ReAuth_GSync-0.1.2.dist-info/METADATA
Auto_ReAuth_GSync-0.1.2.dist-info/WHEEL
Auto_ReAuth_GSync-0.1.2.dist-info/entry_points.txt
Auto_ReAuth_GSync-0.1.2.dist-info/top_level.txt
Auto_ReAuth_GSync-0.1.2.dist-info/RECORD
