Metadata-Version: 2.1
Name: Auto-ReAuth-GSync
Version: 0.1.2
Summary: Google Drive syncing script
Author-email: hengtseChou <hankthedev@gmail.com>
Project-URL: Homepage, https://github.com/hengtseChou/Auto_ReAuth-GSync
Classifier: Programming Language :: Python :: 3
Classifier: License :: OSI Approved :: MIT License
Classifier: Operating System :: OS Independent
Requires-Python: >=3.8
License-File: LICENSE
Requires-Dist: click
Requires-Dist: pydrive2
